sandlerchemeq/__init__.py
sandlerchemeq/chemeqsystem.py
sandlerchemeq/cli.py
sandlerchemeq/component.py
sandlerchemeq/reaction.py
sandlerchemeq-0.2.1.dist-info/METADATA
sandlerchemeq-0.2.1.dist-info/WHEEL
sandlerchemeq-0.2.1.dist-info/entry_points.txt
sandlerchemeq-0.2.1.dist-info/licenses/LICENSE
sandlerchemeq-0.2.1.dist-info/RECORD
