Metadata-Version: 2.4
Name: sandlerchemeq
Version: 0.2.1
Summary: A package implementing computational tools for chemical equilibrium calculations based on Chemical, Biochemical, and Engineering Thermodynamics (5th edition) by Stan Sandler
Author-email: Cameron F Abrams <cfa22@drexel.edu>
License-File: LICENSE
Classifier: License :: OSI Approved :: MIT License
Classifier: Programming Language :: Python :: 3
Requires-Python: >=3.7
Requires-Dist: numpy
Requires-Dist: roman
Requires-Dist: sandlermisc
Requires-Dist: sandlerprops
Requires-Dist: scipy
